refjoin/__init__.py
refjoin/codon_alignment.py
refjoin/constants.py
refjoin/nucleotide_alignment.py
refjoin/read.py
refjoin-0.1.0.dist-info/LICENSE
refjoin-0.1.0.dist-info/METADATA
refjoin-0.1.0.dist-info/WHEEL
refjoin-0.1.0.dist-info/top_level.txt
refjoin-0.1.0.dist-info/RECORD
